tests/__init__.py
tests/test_2.py
zvolv_sdk/__init__.py
zvolv_sdk/version.py
zvolv_sdk/zvolv_client.py
zvolv_sdk/models/__init__.py
zvolv_sdk/models/form.py
zvolv_sdk/models/submission.py
zvolv_sdk/models/task.py
zvolv_sdk/models/user.py
zvolv_sdk/modules/__init__.py
zvolv_sdk/modules/analytics.py
zvolv_sdk/modules/auth.py
zvolv_sdk/modules/communications.py
zvolv_sdk/modules/documents.py
zvolv_sdk/modules/files.py
zvolv_sdk/modules/forms.py
zvolv_sdk/modules/logger.py
zvolv_sdk/modules/roles.py
zvolv_sdk/modules/submissions.py
zvolv_sdk/modules/tasks.py
zvolv_sdk/modules/usergroups.py
zvolv_sdk/modules/users.py
zvolv_sdk/modules/workflows.py
zvolv_sdk/modules/workspace.py
zvolv_sdk/utility/__init__.py
zvolv_sdk/utility/decorators.py
zvolv_sdk/utility/interceptors.py
zvolv_sdk/utility/kafka_handler.py
zvolv_sdk/utility/passwords.py
zvolv_sdk-0.0.50.dist-info/LICENSE
zvolv_sdk-0.0.50.dist-info/METADATA
zvolv_sdk-0.0.50.dist-info/WHEEL
zvolv_sdk-0.0.50.dist-info/top_level.txt
zvolv_sdk-0.0.50.dist-info/RECORD
