Metadata-Version: 2.2
Name: zvolv_sdk
Version: 0.0.50
Summary: The Zvolv API Platform SDK for Python
Home-page: https://github.com/zvolvapi/python-zvolv-sdk
Download-URL: https://github.com/zvolvapi/python-zvolv-sdk/archive/v_01.tar.gz
Author: Akshay Jadhav
Author-email: support@zvolv.com
License: MIT
Keywords: zvolv,zvolv-api,web-api,sdk,rest-api-client
Classifier: Development Status :: 3 - Alpha
Classifier: Intended Audience :: Developers
Classifier: Topic :: Software Development :: Build Tools
Classifier: Operating System :: OS Independent
Classifier: License :: OSI Approved :: MIT License
Classifier: Programming Language :: Python :: 3
Classifier: Programming Language :: Python :: 3.6
Classifier: Programming Language :: Python :: 3.7
Classifier: Programming Language :: Python :: 3.8
Classifier: Programming Language :: Python :: 3.9
Classifier: Programming Language :: Python :: 3.10
Classifier: Programming Language :: Python :: 3.11
Requires-Python: >=3.6.0
License-File: LICENSE
Requires-Dist: requests>=2.23.0
Requires-Dist: pydantic>=2.7.3
Requires-Dist: elasticsearch_dsl>=8.13.1
Dynamic: author
Dynamic: author-email
Dynamic: classifier
Dynamic: description
Dynamic: description-content-type
Dynamic: download-url
Dynamic: home-page
Dynamic: keywords
Dynamic: license
Dynamic: requires-dist
Dynamic: requires-python
Dynamic: summary
